htof/__init__.py
htof/fit.py
htof/main.py
htof/parse.py
htof/settings.py
htof/sky_path.py
htof/special_parse.py
htof/data/__init__.py
htof/data/astrometric_gaps_gaiadr2_08252020.csv
htof/data/astrometric_gaps_gaiaedr3_12232020.csv
htof/data/epoch_reject_shortlist.csv
htof/data/hip1_flagged.txt
htof/data/hip21_java_nobs_discrepant.txt
htof/data/hip2_DVD_flagged.txt
htof/data/hip2_Javatool_flagged.txt
htof/data/hip2_recalibrated_header.txt
htof/polynomial/__init__.py
htof/polynomial/polynomial.py
htof/test/__init__.py
htof/test/test_data_utils.py
htof/test/test_fit.py
htof/test/test_main.py
htof/test/test_parse.py
htof/test/test_polynomial.py
htof/test/test_sky_path.py
htof/test/test_special_parse.py
htof/test/test_utils_ftp.py
htof/utils/__init__.py
htof/utils/data_utils.py
htof/utils/fit_utils.py
htof/utils/ftp.py
htof/utils/parse_utils.py
htof/validation/__init__.py
htof/validation/hip_java_deep_refit.py
htof/validation/hip_refit_test.py
htof/validation/htof_adhoc_correction_f2.py
htof/validation/utils.py
htof-1.1.5.dist-info/LICENSE
htof-1.1.5.dist-info/METADATA
htof-1.1.5.dist-info/WHEEL
htof-1.1.5.dist-info/top_level.txt
htof-1.1.5.dist-info/RECORD
