Metadata-Version: 2.1
Name: htof
Version: 1.1.5
Author: G. Mirek Brandt, Daniel Michalik, Gavin K. Hung
Requires-Python: >=3.6
License-File: LICENSE
Requires-Dist: astropy (>=2.0)
Requires-Dist: pandas (>=0.24.0)
Requires-Dist: scipy (>=1.0.0)
Requires-Dist: numpy (>=1.16)
Requires-Dist: requests
